class_go/__init__.py
class_go/converter.py
class_go/db.py
class_go/schema.py
class_go/scripts.py
classgo-0.2.dev1.dist-info/LICENCE.md
classgo-0.2.dev1.dist-info/METADATA
classgo-0.2.dev1.dist-info/WHEEL
classgo-0.2.dev1.dist-info/entry_points.txt
classgo-0.2.dev1.dist-info/top_level.txt
classgo-0.2.dev1.dist-info/RECORD
