Metadata-Version: 2.1
Name: classgo
Version: 0.2.dev1
Summary: a simplem program to manage class
Home-page: UNKNOWN
Author: Francisco Carvajal Ossa
Author-email: fraco_oxza@outlook.com
License: MIT
Platform: UNKNOWN
Requires-Python: >=3.6
Requires-Dist: click
